package org.apache.cordova;

class null implements Runnable {
  public void run() {
    // Byte code:
    //   0: aload_0
    //   1: monitorenter
    //   2: aload_0
    //   3: aload_0
    //   4: getfield val$loadUrlTimeoutValue : I
    //   7: i2l
    //   8: invokevirtual wait : (J)V
    //   11: aload_0
    //   12: monitorexit
    //   13: goto -> 26
    //   16: astore_1
    //   17: aload_0
    //   18: monitorexit
    //   19: aload_1
    //   20: athrow
    //   21: astore_1
    //   22: aload_1
    //   23: invokevirtual printStackTrace : ()V
    //   26: aload_0
    //   27: getfield this$0 : Lorg/apache/cordova/CordovaWebViewImpl;
    //   30: invokestatic access$100 : (Lorg/apache/cordova/CordovaWebViewImpl;)I
    //   33: aload_0
    //   34: getfield val$currentLoadUrlTimeout : I
    //   37: if_icmpne -> 59
    //   40: aload_0
    //   41: getfield this$0 : Lorg/apache/cordova/CordovaWebViewImpl;
    //   44: invokestatic access$200 : (Lorg/apache/cordova/CordovaWebViewImpl;)Lorg/apache/cordova/CordovaInterface;
    //   47: invokeinterface getActivity : ()Landroid/app/Activity;
    //   52: aload_0
    //   53: getfield val$loadError : Ljava/lang/Runnable;
    //   56: invokevirtual runOnUiThread : (Ljava/lang/Runnable;)V
    //   59: return
    // Exception table:
    //   from	to	target	type
    //   0	2	21	java/lang/InterruptedException
    //   2	13	16	finally
    //   17	19	16	finally
    //   19	21	21	java/lang/InterruptedException
  }
}


/* Location:              C:\Users\Root1\Desktop\Stash\output\!\org\apache\cordova\CordovaWebViewImpl$2.class
 * Java compiler version: 6 (50.0)
 * JD-Core Version:       1.1.3
 */